[
  {"word": "会う", "hiragana": "あう", "meaning": "見面、相遇"},
  {"word": "青", "hiragana": "あお", "meaning": "藍色、青色"},
  {"word": "青い", "hiragana": "あおい", "meaning": "藍的、青的"},
  {"word": "赤", "hiragana": "あか", "meaning": "紅色"},
  {"word": "赤い", "hiragana": "あかい", "meaning": "紅的"},
  {"word": "明い", "hiragana": "あかるい", "meaning": "明亮的"},
  {"word": "秋", "hiragana": "あき", "meaning": "秋天"},
  {"word": "開く", "hiragana": "あく", "meaning": "打開、開"},
  {"word": "開ける", "hiragana": "あける", "meaning": "打開"},
  {"word": "上げる", "hiragana": "あげる", "meaning": "舉起、給"},
  {"word": "朝", "hiragana": "あさ", "meaning": "早上"},
  {"word": "朝御飯", "hiragana": "あさごはん", "meaning": "早飯、早餐"},
  {"word": "あさって", "hiragana": "あさって", "meaning": "後天"},
  {"word": "足", "hiragana": "あし", "meaning": "腳、腿"},
  {"word": "明日", "hiragana": "あした", "meaning": "明天"},
  {"word": "あそこ", "hiragana": "あそこ", "meaning": "那裡"},
  {"word": "遊ぶ", "hiragana": "あそぶ", "meaning": "玩、遊玩"},
  {"word": "暖かい", "hiragana": "あたたかい", "meaning": "溫暖的"},
  {"word": "頭", "hiragana": "あたま", "meaning": "頭"},
  {"word": "新しい", "hiragana": "あたらしい", "meaning": "新的"},
  {"word": "あちら", "hiragana": "あちら", "meaning": "那邊（敬語）"},
  {"word": "暑い", "hiragana": "あつい", "meaning": "熱的（天氣）"},
  {"word": "熱い", "hiragana": "あつい", "meaning": "熱的（物體）"},
  {"word": "厚い", "hiragana": "あつい", "meaning": "厚的"},
  {"word": "あっち", "hiragana": "あっち", "meaning": "那邊"},
  {"word": "後", "hiragana": "あと", "meaning": "後面、之後"},
  {"word": "あなた", "hiragana": "あなた", "meaning": "你"},
  {"word": "兄", "hiragana": "あに", "meaning": "哥哥"},
  {"word": "姉", "hiragana": "あね", "meaning": "姊姊"},
  {"word": "あの", "hiragana": "あの", "meaning": "那個"},
  {"word": "アパート", "hiragana": "アパート", "meaning": "公寓"},
  {"word": "あびる", "hiragana": "あびる", "meaning": "淋浴、沖澡"},
  {"word": "危ない", "hiragana": "あぶない", "meaning": "危險的"},
  {"word": "甘い", "hiragana": "あまい", "meaning": "甜的"},
  {"word": "あまり", "hiragana": "あまり", "meaning": "不太、不怎麼"},
  {"word": "雨", "hiragana": "あめ", "meaning": "雨"},
  {"word": "飴", "hiragana": "あめ", "meaning": "糖果"},
  {"word": "洗う", "hiragana": "あらう", "meaning": "洗"},
  {"word": "ある", "hiragana": "ある", "meaning": "有（無生命）、在"},
  {"word": "歩く", "hiragana": "あるく", "meaning": "走路、步行"},
  {"word": "あれ", "hiragana": "あれ", "meaning": "那個"},
  {"word": "いい/よい", "hiragana": "いい/よい", "meaning": "好的"},
  {"word": "いいえ", "hiragana": "いいえ", "meaning": "不、不是"},
  {"word": "言う", "hiragana": "いう", "meaning": "說"},
  {"word": "家", "hiragana": "いえ", "meaning": "家、房子"},
  {"word": "いかが", "hiragana": "いかが", "meaning": "如何（敬語）"},
  {"word": "行く", "hiragana": "いく", "meaning": "去"},
  {"word": "いくつ", "hiragana": "いくつ", "meaning": "幾個、幾歲"},
  {"word": "いくら", "hiragana": "いくら", "meaning": "多少錢"},
  {"word": "池", "hiragana": "いけ", "meaning": "池塘"},
  {"word": "医者", "hiragana": "いしゃ", "meaning": "醫生"},
  {"word": "いす", "hiragana": "いす", "meaning": "椅子"},
  {"word": "忙しい", "hiragana": "いそがしい", "meaning": "忙碌的"},
  {"word": "痛い", "hiragana": "いたい", "meaning": "痛的"},
  {"word": "一", "hiragana": "いち", "meaning": "一"},
  {"word": "一日", "hiragana": "いちにち", "meaning": "一整天"},
  {"word": "いちばん", "hiragana": "いちばん", "meaning": "最"},
  {"word": "いつ", "hiragana": "いつ", "meaning": "什麼時候"},
  {"word": "五日", "hiragana": "いつか", "meaning": "五號、五日"},
  {"word": "一緒", "hiragana": "いっしょ", "meaning": "一起"},
  {"word": "五つ", "hiragana": "いつつ", "meaning": "五個"},
  {"word": "いつも", "hiragana": "いつも", "meaning": "總是、經常"},
  {"word": "犬", "hiragana": "いぬ", "meaning": "狗"},
  {"word": "今", "hiragana": "いま", "meaning": "現在"},
  {"word": "意味", "hiragana": "いみ", "meaning": "意思、含義"},
  {"word": "妹", "hiragana": "いもうと", "meaning": "妹妹"},
  {"word": "嫌", "hiragana": "いや", "meaning": "討厭、不要"},
  {"word": "入口", "hiragana": "いりぐち", "meaning": "入口"},
  {"word": "居る", "hiragana": "いる", "meaning": "在（有生命）"},
  {"word": "要る", "hiragana": "いる", "meaning": "需要"},
  {"word": "入れる", "hiragana": "いれる", "meaning": "放入"},
  {"word": "色", "hiragana": "いろ", "meaning": "顏色"},
  {"word": "いろいろ", "hiragana": "いろいろ", "meaning": "各種各樣"},
  {"word": "上", "hiragana": "うえ", "meaning": "上面"},
  {"word": "後ろ", "hiragana": "うしろ", "meaning": "後面"},
  {"word": "薄い", "hiragana": "うすい", "meaning": "薄的、淡的"},
  {"word": "歌", "hiragana": "うた", "meaning": "歌"},
  {"word": "歌う", "hiragana": "うたう", "meaning": "唱歌"},
  {"word": "生まれる", "hiragana": "うまれる", "meaning": "出生"},
  {"word": "海", "hiragana": "うみ", "meaning": "海"},
  {"word": "売る", "hiragana": "うる", "meaning": "賣"},
  {"word": "煩い", "hiragana": "うるさい", "meaning": "吵鬧的"},
  {"word": "上着", "hiragana": "うわぎ", "meaning": "外套、上衣"},
  {"word": "絵", "hiragana": "え", "meaning": "畫、圖"},
  {"word": "映画", "hiragana": "えいが", "meaning": "電影"},
  {"word": "映画館", "hiragana": "えいがかん", "meaning": "電影院"},
  {"word": "英語", "hiragana": "えいご", "meaning": "英語"},
  {"word": "ええ", "hiragana": "ええ", "meaning": "是、嗯"},
  {"word": "駅", "hiragana": "えき", "meaning": "車站"},
  {"word": "エレベーター", "hiragana": "エレベーター", "meaning": "電梯"},
  {"word": "鉛筆", "hiragana": "えんぴつ", "meaning": "鉛筆"},
  {"word": "おいしい", "hiragana": "おいしい", "meaning": "好吃的"},
  {"word": "多い", "hiragana": "おおい", "meaning": "多的"},
  {"word": "大きい", "hiragana": "おおきい", "meaning": "大的"},
  {"word": "大きな", "hiragana": "おおきな", "meaning": "大的"},
  {"word": "大勢", "hiragana": "おおぜい", "meaning": "很多人"},
  {"word": "お母さん", "hiragana": "おかあさん", "meaning": "媽媽"},
  {"word": "お菓子", "hiragana": "おかし", "meaning": "點心、零食"},
  {"word": "お金", "hiragana": "おかね", "meaning": "錢"},
  {"word": "起きる", "hiragana": "おきる", "meaning": "起床、發生"},
  {"word": "置く", "hiragana": "おく", "meaning": "放置"},
  {"word": "奥さん", "hiragana": "おくさん", "meaning": "太太（他人的）"},
  {"word": "お酒", "hiragana": "おさけ", "meaning": "酒"},
  {"word": "お皿", "hiragana": "おさら", "meaning": "盤子"},
  {"word": "伯父/叔父", "hiragana": "おじいさん", "meaning": "爺爺、外公"},
  {"word": "教える", "hiragana": "おしえる", "meaning": "教、告訴"},
  {"word": "伯父/叔父", "hiragana": "おじさん", "meaning": "叔叔、伯伯"},
  {"word": "押す", "hiragana": "おす", "meaning": "推、按"},
  {"word": "遅い", "hiragana": "おそい", "meaning": "慢的、遲的"},
  {"word": "お茶", "hiragana": "おちゃ", "meaning": "茶"},
  {"word": "お手洗い", "hiragana": "おてあらい", "meaning": "廁所"},
  {"word": "お父さん", "hiragana": "おとうさん", "meaning": "爸爸"},
  {"word": "弟", "hiragana": "おとうと", "meaning": "弟弟"},
  {"word": "男", "hiragana": "おとこ", "meaning": "男人"},
  {"word": "男の子", "hiragana": "おとこのこ", "meaning": "男孩"},
  {"word": "一昨日", "hiragana": "おととい", "meaning": "前天"},
  {"word": "一昨年", "hiragana": "おととし", "meaning": "前年"},
  {"word": "大人", "hiragana": "おとな", "meaning": "大人"},
  {"word": "おなか", "hiragana": "おなか", "meaning": "肚子"},
  {"word": "同じ", "hiragana": "おなじ", "meaning": "相同的"},
  {"word": "お兄さん", "hiragana": "おにいさん", "meaning": "哥哥（敬稱）"},
  {"word": "お姉さん", "hiragana": "おねえさん", "meaning": "姊姊（敬稱）"},
  {"word": "おばあさん", "hiragana": "おばあさん", "meaning": "奶奶、外婆"},
  {"word": "伯母さん/叔母さん", "hiragana": "おばさん", "meaning": "阿姨、姑姑"},
  {"word": "お風呂", "hiragana": "おふろ", "meaning": "浴缸、洗澡"},
  {"word": "お弁当", "hiragana": "おべんとう", "meaning": "便當"},
  {"word": "覚える", "hiragana": "おぼえる", "meaning": "記住、記得"},
  {"word": "おまわりさん", "hiragana": "おまわりさん", "meaning": "警察"},
  {"word": "重い", "hiragana": "おもい", "meaning": "重的"},
  {"word": "おもしろい", "hiragana": "おもしろい", "meaning": "有趣的"},
  {"word": "泳ぐ", "hiragana": "およぐ", "meaning": "游泳"},
  {"word": "降りる", "hiragana": "おりる", "meaning": "下（車）、下來"},
  {"word": "終る", "hiragana": "おわる", "meaning": "結束"},
  {"word": "音楽", "hiragana": "おんがく", "meaning": "音樂"},
  {"word": "女", "hiragana": "おんな", "meaning": "女人"},
  {"word": "女の子", "hiragana": "おんなのこ", "meaning": "女孩"},
  {"word": "外国", "hiragana": "がいこく", "meaning": "外國"},
  {"word": "外国人", "hiragana": "がいこくじん", "meaning": "外國人"},
  {"word": "会社", "hiragana": "かいしゃ", "meaning": "公司"},
  {"word": "階段", "hiragana": "かいだん", "meaning": "樓梯"},
  {"word": "買い物", "hiragana": "かいもの", "meaning": "購物"},
  {"word": "買う", "hiragana": "かう", "meaning": "買"},
  {"word": "返す", "hiragana": "かえす", "meaning": "還、歸還"},
  {"word": "帰る", "hiragana": "かえる", "meaning": "回去、回家"},
  {"word": "かかる", "hiragana": "かかる", "meaning": "花費（時間、金錢）"},
  {"word": "かぎ", "hiragana": "かぎ", "meaning": "鑰匙"},
  {"word": "書く", "hiragana": "かく", "meaning": "寫"},
  {"word": "学生", "hiragana": "がくせい", "meaning": "學生"},
  {"word": "かける", "hiragana": "かける", "meaning": "打（電話）、掛"},
  {"word": "傘", "hiragana": "かさ", "meaning": "雨傘"},
  {"word": "貸す", "hiragana": "かす", "meaning": "借（給別人）"},
  {"word": "風", "hiragana": "かぜ", "meaning": "風"},
  {"word": "風邪", "hiragana": "かぜ", "meaning": "感冒"},
  {"word": "家族", "hiragana": "かぞく", "meaning": "家人"},
  {"word": "方", "hiragana": "かた", "meaning": "方向、方法、人（敬稱）"},
  {"word": "学校", "hiragana": "がっこう", "meaning": "學校"},
  {"word": "カップ", "hiragana": "カップ", "meaning": "杯子"},
  {"word": "家庭", "hiragana": "かてい", "meaning": "家庭"},
  {"word": "角", "hiragana": "かど", "meaning": "轉角"},
  {"word": "かばん", "hiragana": "かばん", "meaning": "包包"},
  {"word": "花瓶", "hiragana": "かびん", "meaning": "花瓶"},
  {"word": "紙", "hiragana": "かみ", "meaning": "紙"},
  {"word": "カメラ", "hiragana": "カメラ", "meaning": "相機"},
  {"word": "火曜日", "hiragana": "かようび", "meaning": "星期二"},
  {"word": "辛い", "hiragana": "からい", "meaning": "辣的"},
  {"word": "体", "hiragana": "からだ", "meaning": "身體"},
  {"word": "借りる", "hiragana": "かりる", "meaning": "借（向別人借）"},
  {"word": "軽い", "hiragana": "かるい", "meaning": "輕的"},
  {"word": "カレー", "hiragana": "カレー", "meaning": "咖哩"},
  {"word": "カレンダー", "hiragana": "カレンダー", "meaning": "日曆"},
  {"word": "川/河", "hiragana": "かわ", "meaning": "河川"},
  {"word": "かわいい", "hiragana": "かわいい", "meaning": "可愛的"},
  {"word": "漢字", "hiragana": "かんじ", "meaning": "漢字"},
  {"word": "木", "hiragana": "き", "meaning": "樹木"},
  {"word": "黄色", "hiragana": "きいろ", "meaning": "黃色"},
  {"word": "黄色い", "hiragana": "きいろい", "meaning": "黃色的"},
  {"word": "消える", "hiragana": "きえる", "meaning": "消失"},
  {"word": "聞く", "hiragana": "きく", "meaning": "聽、問"},
  {"word": "北", "hiragana": "きた", "meaning": "北方"},
  {"word": "ギター", "hiragana": "ギター", "meaning": "吉他"},
  {"word": "汚い", "hiragana": "きたない", "meaning": "髒的"},
  {"word": "喫茶店", "hiragana": "きっさてん", "meaning": "咖啡廳、茶館"},
  {"word": "切手", "hiragana": "きって", "meaning": "郵票"},
  {"word": "切符", "hiragana": "きっぷ", "meaning": "車票"},
  {"word": "昨日", "hiragana": "きのう", "meaning": "昨天"},
  {"word": "九", "hiragana": "きゅう / く", "meaning": "九"},
  {"word": "牛肉", "hiragana": "ぎゅうにく", "meaning": "牛肉"},
  {"word": "牛乳", "hiragana": "ぎゅうにゅう", "meaning": "牛奶"},
  {"word": "今日", "hiragana": "きょう", "meaning": "今天"},
  {"word": "教室", "hiragana": "きょうしつ", "meaning": "教室"},
  {"word": "兄弟", "hiragana": "きょうだい", "meaning": "兄弟姊妹"},
  {"word": "去年", "hiragana": "きょねん", "meaning": "去年"},
  {"word": "嫌い", "hiragana": "きらい", "meaning": "討厭"},
  {"word": "切る", "hiragana": "きる", "meaning": "切、剪"},
  {"word": "着る", "hiragana": "きる", "meaning": "穿（上衣）"},
  {"word": "きれい", "hiragana": "きれい", "meaning": "漂亮的、乾淨的"},
  {"word": "キロ/キログラム", "hiragana": "キロ/キログラム", "meaning": "公斤"},
  {"word": "キロ/キロメートル", "hiragana": "キロ/キロメートル", "meaning": "公里"},
  {"word": "銀行", "hiragana": "ぎんこう", "meaning": "銀行"},
  {"word": "金曜日", "hiragana": "きんようび", "meaning": "星期五"},
  {"word": "薬", "hiragana": "くすり", "meaning": "藥"},
  {"word": "ください", "hiragana": "ください", "meaning": "請給我"},
  {"word": "果物", "hiragana": "くだもの", "meaning": "水果"},
  {"word": "口", "hiragana": "くち", "meaning": "嘴巴"},
  {"word": "靴", "hiragana": "くつ", "meaning": "鞋子"},
  {"word": "靴下", "hiragana": "くつした", "meaning": "襪子"},
  {"word": "国", "hiragana": "くに", "meaning": "國家"},
  {"word": "曇り", "hiragana": "くもり", "meaning": "陰天"},
  {"word": "曇る", "hiragana": "くもる", "meaning": "天空變陰"},
  {"word": "暗い", "hiragana": "くらい", "meaning": "暗的"},
  {"word": "クラス", "hiragana": "クラス", "meaning": "班級"},
  {"word": "グラム", "hiragana": "グラム", "meaning": "公克"},
  {"word": "来る", "hiragana": "くる", "meaning": "來"},
  {"word": "車", "hiragana": "くるま", "meaning": "車"},
  {"word": "黒", "hiragana": "くろ", "meaning": "黑色"},
  {"word": "黒い", "hiragana": "くろい", "meaning": "黑色的"},
  {"word": "警官", "hiragana": "けいかん", "meaning": "警察"},
  {"word": "今朝", "hiragana": "けさ", "meaning": "今天早上"},
  {"word": "消す", "hiragana": "けす", "meaning": "關掉、擦掉"},
  {"word": "結構", "hiragana": "けっこう", "meaning": "相當、不用了"},
  {"word": "結婚", "hiragana": "けっこん", "meaning": "結婚"},
  {"word": "月曜日", "hiragana": "げつようび", "meaning": "星期一"},
  {"word": "玄関", "hiragana": "げんかん", "meaning": "玄關"},
  {"word": "元気", "hiragana": "げんき", "meaning": "精神好、健康"},
  {"word": "五", "hiragana": "ご", "meaning": "五"},
  {"word": "公園", "hiragana": "こうえん", "meaning": "公園"},
  {"word": "交差点", "hiragana": "こうさてん", "meaning": "十字路口"},
  {"word": "紅茶", "hiragana": "こうちゃ", "meaning": "紅茶"},
  {"word": "交番", "hiragana": "こうばん", "meaning": "派出所"},
  {"word": "声", "hiragana": "こえ", "meaning": "聲音"},
  {"word": "コート", "hiragana": "コート", "meaning": "大衣、外套"},
  {"word": "コーヒー", "hiragana": "コーヒー", "meaning": "咖啡"},
  {"word": "ここ", "hiragana": "ここ", "meaning": "這裡"},
  {"word": "午後", "hiragana": "ごご", "meaning": "下午"},
  {"word": "九日", "hiragana": "ここのか", "meaning": "九號"},
  {"word": "九つ", "hiragana": "ここのつ", "meaning": "九個"},
  {"word": "午前", "hiragana": "ごぜん", "meaning": "上午"},
  {"word": "答える", "hiragana": "こたえる", "meaning": "回答"},
  {"word": "こちら", "hiragana": "こちら", "meaning": "這邊（敬語）"},
  {"word": "こっち", "hiragana": "こっち", "meaning": "這邊"},
  {"word": "コップ", "hiragana": "コップ", "meaning": "玻璃杯"},
  {"word": "今年", "hiragana": "ことし", "meaning": "今年"},
  {"word": "言葉", "hiragana": "ことば", "meaning": "語言、詞語"},
  {"word": "子供", "hiragana": "こども", "meaning": "小孩"},
  {"word": "この", "hiragana": "この", "meaning": "這個"},
  {"word": "御飯", "hiragana": "ごはん", "meaning": "飯、餐"},
  {"word": "コピーする", "hiragana": "コピーする", "meaning": "影印、複製"},
  {"word": "困る", "hiragana": "こまる", "meaning": "困擾、為難"},
  {"word": "これ", "hiragana": "これ", "meaning": "這個"},
  {"word": "今月", "hiragana": "こんげつ", "meaning": "本月"},
  {"word": "今週", "hiragana": "こんしゅう", "meaning": "本週"},
  {"word": "こんな", "hiragana": "こんな", "meaning": "這樣的"},
  {"word": "今晩", "hiragana": "こんばん", "meaning": "今晚"},
  {"word": "さあ", "hiragana": "さあ", "meaning": "好吧、來吧"},
  {"word": "財布", "hiragana": "さいふ", "meaning": "錢包"},
  {"word": "魚", "hiragana": "さかな", "meaning": "魚"},
  {"word": "先", "hiragana": "さき", "meaning": "前方、先"},
  {"word": "咲く", "hiragana": "さく", "meaning": "（花）開"},
  {"word": "作文", "hiragana": "さくぶん", "meaning": "作文"},
  {"word": "差す", "hiragana": "さす", "meaning": "撐傘"},
  {"word": "雑誌", "hiragana": "ざっし", "meaning": "雜誌"},
  {"word": "砂糖", "hiragana": "さとう", "meaning": "砂糖"},
  {"word": "寒い", "hiragana": "さむい", "meaning": "冷的"},
  {"word": "さ来年", "hiragana": "さらいねん", "meaning": "後年"},
  {"word": "三", "hiragana": "さん", "meaning": "三"},
  {"word": "散歩", "hiragana": "さんぽする", "meaning": "散步"},
  {"word": "四", "hiragana": "し / よん", "meaning": "四"},
  {"word": "塩", "hiragana": "しお", "meaning": "鹽"},
  {"word": "しかし", "hiragana": "しかし", "meaning": "但是、然而"},
  {"word": "時間", "hiragana": "じかん", "meaning": "時間"},
  {"word": "仕事", "hiragana": "しごと", "meaning": "工作"},
  {"word": "辞書", "hiragana": "じしょ", "meaning": "字典"},
  {"word": "静か", "hiragana": "しずか", "meaning": "安靜的"},
  {"word": "下", "hiragana": "した", "meaning": "下面"},
  {"word": "七", "hiragana": "しち / なな", "meaning": "七"},
  {"word": "質問", "hiragana": "しつもん", "meaning": "問題、提問"},
  {"word": "自転車", "hiragana": "じてんしゃ", "meaning": "腳踏車"},
  {"word": "自動車", "hiragana": "じどうしゃ", "meaning": "汽車"},
  {"word": "死ぬ", "hiragana": "しぬ", "meaning": "死"},
  {"word": "字引", "hiragana": "じびき", "meaning": "字典"},
  {"word": "自分", "hiragana": "じぶん", "meaning": "自己"},
  {"word": "閉まる", "hiragana": "しまる", "meaning": "關閉（自動）"},
  {"word": "閉める", "hiragana": "しめる", "meaning": "關閉（手動）"},
  {"word": "締める", "hiragana": "しめる", "meaning": "繫、扣"},
  {"word": "じゃ/じゃあ", "hiragana": "じゃ/じゃあ", "meaning": "那麼"},
  {"word": "写真", "hiragana": "しゃしん", "meaning": "照片"},
  {"word": "シャツ", "hiragana": "シャツ", "meaning": "襯衫"},
  {"word": "シャワー", "hiragana": "シャワー", "meaning": "淋浴"},
  {"word": "十", "hiragana": "じゅう とお", "meaning": "十"},
  {"word": "授業", "hiragana": "じゅぎょう", "meaning": "課程、上課"},
  {"word": "宿題", "hiragana": "しゅくだい", "meaning": "作業"},
  {"word": "上手", "hiragana": "じょうず", "meaning": "擅長、高明"},
  {"word": "丈夫", "hiragana": "じょうぶ", "meaning": "堅固的、結實的"},
  {"word": "しょうゆ", "hiragana": "しょうゆ", "meaning": "醬油"},
  {"word": "食堂", "hiragana": "しょくどう", "meaning": "食堂、餐廳"},
  {"word": "知る", "hiragana": "しる", "meaning": "知道"},
  {"word": "白", "hiragana": "しろ", "meaning": "白色"},
  {"word": "白い", "hiragana": "しろい", "meaning": "白色的"},
  {"word": "新聞", "hiragana": "しんぶん", "meaning": "報紙"},
  {"word": "水曜日", "hiragana": "すいようび", "meaning": "星期三"},
  {"word": "吸う", "hiragana": "すう", "meaning": "吸（煙）"},
  {"word": "スカート", "hiragana": "スカート", "meaning": "裙子"},
  {"word": "好き", "hiragana": "すき", "meaning": "喜歡"},
  {"word": "少ない", "hiragana": "すくない", "meaning": "少的"},
  {"word": "すぐに", "hiragana": "すぐに", "meaning": "馬上、立刻"},
  {"word": "少し", "hiragana": "すこし", "meaning": "一點、稍微"},
  {"word": "涼しい", "hiragana": "すずしい", "meaning": "涼快的"},
  {"word": "ストーブ", "hiragana": "ストーブ", "meaning": "暖爐"},
  {"word": "スプーン", "hiragana": "スプーン", "meaning": "湯匙"},
  {"word": "スポーツ", "hiragana": "スポーツ", "meaning": "運動"},
  {"word": "ズボン", "hiragana": "ズボン", "meaning": "褲子"},
  {"word": "住む", "hiragana": "すむ", "meaning": "居住"},
  {"word": "スリッパ", "hiragana": "スリッパ", "meaning": "拖鞋"},
  {"word": "する", "hiragana": "する", "meaning": "做"},
  {"word": "座る", "hiragana": "すわる", "meaning": "坐"},
  {"word": "背", "hiragana": "せ", "meaning": "身高、背"},
  {"word": "生徒", "hiragana": "せいと", "meaning": "學生（中小學）"},
  {"word": "セーター", "hiragana": "セーター", "meaning": "毛衣"},
  {"word": "せっけん", "hiragana": "せっけん", "meaning": "肥皂"},
  {"word": "背広", "hiragana": "せびろ", "meaning": "西裝"},
  {"word": "狭い", "hiragana": "せまい", "meaning": "狹窄的"},
  {"word": "ゼロ", "hiragana": "ゼロ", "meaning": "零"},
  {"word": "千", "hiragana": "せん", "meaning": "千"},
  {"word": "先月", "hiragana": "せんげつ", "meaning": "上個月"},
  {"word": "先週", "hiragana": "せんしゅう", "meaning": "上週"},
  {"word": "先生", "hiragana": "せんせい", "meaning": "老師"},
  {"word": "洗濯", "hiragana": "せんたく", "meaning": "洗衣服"},
  {"word": "全部", "hiragana": "ぜんぶ", "meaning": "全部"},
  {"word": "掃除", "hiragana": "そうじする", "meaning": "打掃"},
  {"word": "そうして/そして", "hiragana": "そうして/そして", "meaning": "然後、接著"},
  {"word": "そこ", "hiragana": "そこ", "meaning": "那裡"},
  {"word": "そちら", "hiragana": "そちら", "meaning": "那邊（敬語）"},
  {"word": "そっち", "hiragana": "そっち", "meaning": "那邊"},
  {"word": "外", "hiragana": "そと", "meaning": "外面"},
  {"word": "その", "hiragana": "その", "meaning": "那個"},
  {"word": "そば", "hiragana": "そば", "meaning": "旁邊、蕎麥麵"},
  {"word": "空", "hiragana": "そら", "meaning": "天空"},
  {"word": "それ", "hiragana": "それ", "meaning": "那個"},
  {"word": "それから", "hiragana": "それから", "meaning": "然後、從那之後"},
  {"word": "それでは", "hiragana": "それでは", "meaning": "那麼、這樣的話"},
  {"word": "大学", "hiragana": "だいがく", "meaning": "大學"},
  {"word": "大使館", "hiragana": "たいしかん", "meaning": "大使館"},
  {"word": "大丈夫", "hiragana": "だいじょうぶ", "meaning": "沒問題、沒關係"},
  {"word": "大好き", "hiragana": "だいすき", "meaning": "非常喜歡"},
  {"word": "大切", "hiragana": "たいせつ", "meaning": "重要的"},
  {"word": "台所", "hiragana": "だいどころ", "meaning": "廚房"},
  {"word": "たいへん", "hiragana": "たいへん", "meaning": "非常、辛苦"},
  {"word": "高い", "hiragana": "たかい", "meaning": "高的、貴的"},
  {"word": "たくさん", "hiragana": "たくさん", "meaning": "很多"},
  {"word": "タクシー", "hiragana": "タクシー", "meaning": "計程車"},
  {"word": "出す", "hiragana": "だす", "meaning": "拿出、提交"},
  {"word": "立つ", "hiragana": "たつ", "meaning": "站立"},
  {"word": "たて", "hiragana": "たて", "meaning": "縱向"},
  {"word": "建物", "hiragana": "たてもの", "meaning": "建築物"},
  {"word": "楽しい", "hiragana": "たのしい", "meaning": "快樂的"},
  {"word": "頼む", "hiragana": "たのむ", "meaning": "拜託、請求"},
  {"word": "たばこ", "hiragana": "たばこ", "meaning": "香菸"},
  {"word": "たぶん", "hiragana": "たぶん", "meaning": "大概、也許"},
  {"word": "食べ物", "hiragana": "たべもの", "meaning": "食物"},
  {"word": "食べる", "hiragana": "たべる", "meaning": "吃"},
  {"word": "卵", "hiragana": "たまご", "meaning": "雞蛋"},
  {"word": "誰", "hiragana": "だれ", "meaning": "誰"},
  {"word": "誰", "hiragana": "だれか", "meaning": "某人"},
  {"word": "誕生日", "hiragana": "たんじょうび", "meaning": "生日"},
  {"word": "だんだん", "hiragana": "だんだん", "meaning": "漸漸地"},
  {"word": "小さい", "hiragana": "ちいさい", "meaning": "小的"},
  {"word": "小さな", "hiragana": "ちいさな", "meaning": "小的"},
  {"word": "近い", "hiragana": "ちかい", "meaning": "近的"},
  {"word": "違う", "hiragana": "ちがう", "meaning": "不同、不對"},
  {"word": "近く", "hiragana": "ちかく", "meaning": "附近"},
  {"word": "地下鉄", "hiragana": "ちかてつ", "meaning": "地鐵"},
  {"word": "地図", "hiragana": "ちず", "meaning": "地圖"},
  {"word": "茶色", "hiragana": "ちゃいろ", "meaning": "茶色、棕色"},
  {"word": "ちゃわん", "hiragana": "ちゃわん", "meaning": "碗"},
  {"word": "ちょうど", "hiragana": "ちょうど", "meaning": "剛好、正好"},
  {"word": "ちょっと", "hiragana": "ちょっと", "meaning": "一點、稍微"},
  {"word": "一日", "hiragana": "ついたち", "meaning": "一號"},
  {"word": "使う", "hiragana": "つかう", "meaning": "使用"},
  {"word": "疲れる", "hiragana": "つかれる", "meaning": "疲累"},
  {"word": "次", "hiragana": "つぎ", "meaning": "下一個"},
  {"word": "着く", "hiragana": "つく", "meaning": "到達"},
  {"word": "机", "hiragana": "つくえ", "meaning": "桌子"},
  {"word": "作る", "hiragana": "つくる", "meaning": "製作、做"},
  {"word": "つける", "hiragana": "つける", "meaning": "打開、開啟"},
  {"word": "勤める", "hiragana": "つとめる", "meaning": "任職、工作"},
  {"word": "つまらない", "hiragana": "つまらない", "meaning": "無聊的"},
  {"word": "冷たい", "hiragana": "つめたい", "meaning": "冰涼的"},
  {"word": "強い", "hiragana": "つよい", "meaning": "強的"},
  {"word": "手", "hiragana": "て", "meaning": "手"},
  {"word": "テープ", "hiragana": "テープ", "meaning": "膠帶"},
  {"word": "テーブル", "hiragana": "テーブル", "meaning": "桌子"},
  {"word": "テープレコーダー", "hiragana": "テープレコーダー", "meaning": "錄音機"},
  {"word": "出かける", "hiragana": "でかける", "meaning": "外出"},
  {"word": "手紙", "hiragana": "てがみ", "meaning": "信件"},
  {"word": "できる", "hiragana": "できる", "meaning": "能夠、會"},
  {"word": "出口", "hiragana": "でぐち", "meaning": "出口"},
  {"word": "テスト", "hiragana": "テスト", "meaning": "考試、測驗"},
  {"word": "では", "hiragana": "では", "meaning": "那麼"},
  {"word": "デパート", "hiragana": "デパート", "meaning": "百貨公司"},
  {"word": "でも", "hiragana": "でも", "meaning": "但是"},
  {"word": "出る", "hiragana": "でる", "meaning": "出去、出現"},
  {"word": "テレビ", "hiragana": "テレビ", "meaning": "電視"},
  {"word": "天気", "hiragana": "てんき", "meaning": "天氣"},
  {"word": "電気", "hiragana": "でんき", "meaning": "電、電燈"},
  {"word": "電車", "hiragana": "でんしゃ", "meaning": "電車"},
  {"word": "電話", "hiragana": "でんわ", "meaning": "電話"},
  {"word": "戸", "hiragana": "と", "meaning": "門"},
  {"word": "ドア", "hiragana": "ドア", "meaning": "門"},
  {"word": "トイレ", "hiragana": "トイレ", "meaning": "廁所"},
  {"word": "どう", "hiragana": "どう", "meaning": "怎麼、如何"},
  {"word": "どうして", "hiragana": "どうして", "meaning": "為什麼"},
  {"word": "どうぞ", "hiragana": "どうぞ", "meaning": "請"},
  {"word": "動物", "hiragana": "どうぶつ", "meaning": "動物"},
  {"word": "どうも", "hiragana": "どうも", "meaning": "謝謝、非常"},
  {"word": "遠い", "hiragana": "とおい", "meaning": "遠的"},
  {"word": "十日", "hiragana": "とおか", "meaning": "十號"},
  {"word": "時々", "hiragana": "ときどき", "meaning": "有時候"},
  {"word": "時計", "hiragana": "とけい", "meaning": "時鐘、手錶"},
  {"word": "どこ", "hiragana": "どこ", "meaning": "哪裡"},
  {"word": "所", "hiragana": "ところ", "meaning": "地方"},
  {"word": "年", "hiragana": "とし", "meaning": "年、年齡"},
  {"word": "図書館", "hiragana": "としょかん", "meaning": "圖書館"},
  {"word": "どちら", "hiragana": "どちら", "meaning": "哪邊（敬語）"},
  {"word": "どっち", "hiragana": "どっち", "meaning": "哪邊"},
  {"word": "とても", "hiragana": "とても", "meaning": "非常"},
  {"word": "どなた", "hiragana": "どなた", "meaning": "哪位（敬語）"},
  {"word": "隣", "hiragana": "となり", "meaning": "隔壁"},
  {"word": "どの", "hiragana": "どの", "meaning": "哪個"},
  {"word": "飛ぶ", "hiragana": "とぶ", "meaning": "飛"},
  {"word": "止まる", "hiragana": "とまる", "meaning": "停止"},
  {"word": "友達", "hiragana": "ともだち", "meaning": "朋友"},
  {"word": "土曜日", "hiragana": "どようび", "meaning": "星期六"},
  {"word": "鳥", "hiragana": "とり", "meaning": "鳥"},
  {"word": "とり肉", "hiragana": "とりにく", "meaning": "雞肉"},
  {"word": "取る", "hiragana": "とる", "meaning": "拿取"},
  {"word": "撮る", "hiragana": "とる", "meaning": "拍照"},
  {"word": "どれ", "hiragana": "どれ", "meaning": "哪個"},
  {"word": "ナイフ", "hiragana": "ナイフ", "meaning": "刀子"},
  {"word": "中", "hiragana": "なか", "meaning": "裡面"},
  {"word": "長い", "hiragana": "ながい", "meaning": "長的"},
  {"word": "鳴く", "hiragana": "なく", "meaning": "（動物）叫"},
  {"word": "無くす", "hiragana": "なくす", "meaning": "弄丟"},
  {"word": "なぜ", "hiragana": "なぜ", "meaning": "為什麼"},
  {"word": "夏", "hiragana": "なつ", "meaning": "夏天"},
  {"word": "夏休み", "hiragana": "なつやすみ", "meaning": "暑假"},
  {"word": "など", "hiragana": "など", "meaning": "等等"},
  {"word": "七つ", "hiragana": "ななつ", "meaning": "七個"},
  {"word": "七日", "hiragana": "なのか", "meaning": "七號"},
  {"word": "名前", "hiragana": "なまえ", "meaning": "名字"},
  {"word": "習う", "hiragana": "ならう", "meaning": "學習"},
  {"word": "並ぶ", "hiragana": "ならぶ", "meaning": "排隊、排列"},
  {"word": "並べる", "hiragana": "ならべる", "meaning": "排列"},
  {"word": "なる", "hiragana": "なる", "meaning": "變成"},
  {"word": "何", "hiragana": "なん/なに", "meaning": "什麼"},
  {"word": "二", "hiragana": "に", "meaning": "二"},
  {"word": "賑やか", "hiragana": "にぎやか", "meaning": "熱鬧的"},
  {"word": "肉", "hiragana": "にく", "meaning": "肉"},
  {"word": "西", "hiragana": "にし", "meaning": "西方"},
  {"word": "日曜日", "hiragana": "にちようび", "meaning": "星期日"},
  {"word": "荷物", "hiragana": "にもつ", "meaning": "行李"},
  {"word": "ニュース", "hiragana": "ニュース", "meaning": "新聞"},
  {"word": "庭", "hiragana": "にわ", "meaning": "庭院"},
  {"word": "脱ぐ", "hiragana": "ぬぐ", "meaning": "脫（衣服）"},
  {"word": "温い", "hiragana": "ぬるい", "meaning": "溫的"},
  {"word": "ネクタイ", "hiragana": "ネクタイ", "meaning": "領帶"},
  {"word": "猫", "hiragana": "ねこ", "meaning": "貓"},
  {"word": "寝る", "hiragana": "ねる", "meaning": "睡覺"},
  {"word": "ノート", "hiragana": "ノート", "meaning": "筆記本"},
  {"word": "登る", "hiragana": "のぼる", "meaning": "爬上、登"},
  {"word": "飲み物", "hiragana": "のみもの", "meaning": "飲料"},
  {"word": "飲む", "hiragana": "のむ", "meaning": "喝"},
  {"word": "乗る", "hiragana": "のる", "meaning": "搭乘"},
  {"word": "歯", "hiragana": "は", "meaning": "牙齒"},
  {"word": "パーティー", "hiragana": "パーティー", "meaning": "派對"},
  {"word": "はい", "hiragana": "はい", "meaning": "是"},
  {"word": "灰皿", "hiragana": "はいざら", "meaning": "菸灰缸"},
  {"word": "入る", "hiragana": "はいる", "meaning": "進入"},
  {"word": "葉書", "hiragana": "はがき", "meaning": "明信片"},
  {"word": "はく", "hiragana": "はく", "meaning": "穿（褲子、鞋子）"},
  {"word": "箱", "hiragana": "はこ", "meaning": "箱子"},
  {"word": "橋", "hiragana": "はし", "meaning": "橋"},
  {"word": "はし", "hiragana": "はし", "meaning": "筷子"},
  {"word": "始まる", "hiragana": "はじまる", "meaning": "開始（自動）"},
  {"word": "初め/始め", "hiragana": "はじめ", "meaning": "開始、最初"},
  {"word": "初めて", "hiragana": "はじめて", "meaning": "第一次"},
  {"word": "走る", "hiragana": "はしる", "meaning": "跑"},
  {"word": "バス", "hiragana": "バス", "meaning": "公車"},
  {"word": "バター", "hiragana": "バター", "meaning": "奶油"},
  {"word": "二十歳", "hiragana": "はたち", "meaning": "二十歲"},
  {"word": "働く", "hiragana": "はたらく", "meaning": "工作"},
  {"word": "八", "hiragana": "はち", "meaning": "八"},
  {"word": "二十日", "hiragana": "はつか", "meaning": "二十號"},
  {"word": "花", "hiragana": "はな", "meaning": "花"},
  {"word": "鼻", "hiragana": "はな", "meaning": "鼻子"},
  {"word": "話", "hiragana": "はなし", "meaning": "話、故事"},
  {"word": "話す", "hiragana": "はなす", "meaning": "說話"},
  {"word": "早い", "hiragana": "はやい", "meaning": "早的"},
  {"word": "速い", "hiragana": "はやい", "meaning": "快的"},
  {"word": "春", "hiragana": "はる", "meaning": "春天"},
  {"word": "貼る", "hiragana": "はる", "meaning": "貼"},
  {"word": "晴れ", "hiragana": "はれ", "meaning": "晴天"},
  {"word": "晴れる", "hiragana": "はれる", "meaning": "放晴"},
  {"word": "半", "hiragana": "はん", "meaning": "半"},
  {"word": "晩", "hiragana": "ばん", "meaning": "晚上"},
  {"word": "パン", "hiragana": "パン", "meaning": "麵包"},
  {"word": "ハンカチ", "hiragana": "ハンカチ", "meaning": "手帕"},
  {"word": "番号", "hiragana": "ばんごう", "meaning": "號碼"},
  {"word": "晩御飯", "hiragana": "ばんごはん", "meaning": "晚餐"},
  {"word": "半分", "hiragana": "はんぶん", "meaning": "一半"},
  {"word": "東", "hiragana": "ひがし", "meaning": "東方"},
  {"word": "引く", "hiragana": "ひく", "meaning": "拉、查（字典）"},
  {"word": "弾く", "hiragana": "ひく", "meaning": "彈（樂器）"},
  {"word": "低い", "hiragana": "ひくい", "meaning": "低的"},
  {"word": "飛行機", "hiragana": "ひこうき", "meaning": "飛機"},
  {"word": "左", "hiragana": "ひだり", "meaning": "左邊"},
  {"word": "人", "hiragana": "ひと", "meaning": "人"},
  {"word": "一つ", "hiragana": "ひとつ", "meaning": "一個"},
  {"word": "一月", "hiragana": "ひとつき", "meaning": "一個月"},
  {"word": "一人", "hiragana": "ひとり", "meaning": "一個人"},
  {"word": "暇", "hiragana": "ひま", "meaning": "空閒"},
  {"word": "百", "hiragana": "ひゃく", "meaning": "百"},
  {"word": "病院", "hiragana": "びょういん", "meaning": "醫院"},
  {"word": "病気", "hiragana": "びょうき", "meaning": "生病"},
  {"word": "昼", "hiragana": "ひる", "meaning": "中午"},
  {"word": "昼御飯", "hiragana": "ひるごはん", "meaning": "午餐"},
  {"word": "広い", "hiragana": "ひろい", "meaning": "寬廣的"},
  {"word": "フィルム", "hiragana": "フィルム", "meaning": "底片"},
  {"word": "封筒", "hiragana": "ふうとう", "meaning": "信封"},
  {"word": "プール", "hiragana": "プール", "meaning": "游泳池"},
  {"word": "フォーク", "hiragana": "フォーク", "meaning": "叉子"},
  {"word": "吹く", "hiragana": "ふく", "meaning": "吹"},
  {"word": "服", "hiragana": "ふく", "meaning": "衣服"},
  {"word": "二つ", "hiragana": "ふたつ", "meaning": "兩個"},
  {"word": "豚肉", "hiragana": "ぶたにく", "meaning": "豬肉"},
  {"word": "二人", "hiragana": "ふたり", "meaning": "兩個人"},
  {"word": "二日", "hiragana": "ふつか", "meaning": "二號"},
  {"word": "太い", "hiragana": "ふとい", "meaning": "粗的"},
  {"word": "冬", "hiragana": "ふゆ", "meaning": "冬天"},
  {"word": "降る", "hiragana": "ふる", "meaning": "（雨、雪）下"},
  {"word": "古い", "hiragana": "ふるい", "meaning": "舊的"},
  {"word": "ふろ", "hiragana": "ふろ", "meaning": "浴室、洗澡"},
  {"word": "文章", "hiragana": "ぶんしょう", "meaning": "文章"},
  {"word": "ページ", "hiragana": "ページ", "meaning": "頁"},
  {"word": "下手", "hiragana": "へた", "meaning": "不擅長"},
  {"word": "ベッド", "hiragana": "ベッド", "meaning": "床"},
  {"word": "ペット", "hiragana": "ペット", "meaning": "寵物"},
  {"word": "部屋", "hiragana": "へや", "meaning": "房間"},
  {"word": "辺", "hiragana": "へん", "meaning": "附近、一帶"},
  {"word": "ペン", "hiragana": "ペン", "meaning": "筆"},
  {"word": "勉強", "hiragana": "べんきょうする", "meaning": "讀書、學習"},
  {"word": "便利", "hiragana": "べんり", "meaning": "方便的"},
  {"word": "帽子", "hiragana": "ぼうし", "meaning": "帽子"},
  {"word": "ボールペン", "hiragana": "ボールペン", "meaning": "原子筆"},
  {"word": "ほか", "hiragana": "ほか", "meaning": "其他"},
  {"word": "ポケット", "hiragana": "ポケット", "meaning": "口袋"},
  {"word": "欲しい", "hiragana": "ほしい", "meaning": "想要"},
  {"word": "ポスト", "hiragana": "ポスト", "meaning": "郵筒"},
  {"word": "細い", "hiragana": "ほそい", "meaning": "細的"},
  {"word": "ボタン", "hiragana": "ボタン", "meaning": "按鈕、鈕扣"},
  {"word": "ホテル", "hiragana": "ホテル", "meaning": "飯店"},
  {"word": "本", "hiragana": "ほん", "meaning": "書"},
  {"word": "本棚", "hiragana": "ほんだな", "meaning": "書架"},
  {"word": "ほんとう", "hiragana": "ほんとう", "meaning": "真的"},
  {"word": "毎朝", "hiragana": "まいあさ", "meaning": "每天早上"},
  {"word": "毎月", "hiragana": "まいげつ/まいつき", "meaning": "每個月"},
  {"word": "毎週", "hiragana": "まいしゅう", "meaning": "每週"},
  {"word": "毎日", "hiragana": "まいにち", "meaning": "每天"},
  {"word": "毎年", "hiragana": "まいねん/まいとし", "meaning": "每年"},
  {"word": "毎晩", "hiragana": "まいばん", "meaning": "每天晚上"},
  {"word": "前", "hiragana": "まえ", "meaning": "前面"},
  {"word": "曲る", "hiragana": "まがる", "meaning": "轉彎"},
  {"word": "まずい", "hiragana": "まずい", "meaning": "難吃的"},
  {"word": "また", "hiragana": "また", "meaning": "又、再"},
  {"word": "まだ", "hiragana": "まだ", "meaning": "還、仍然"},
  {"word": "町", "hiragana": "まち", "meaning": "城鎮"},
  {"word": "待つ", "hiragana": "まつ", "meaning": "等待"},
  {"word": "まっすぐ", "hiragana": "まっすぐ", "meaning": "直走、筆直"},
  {"word": "マッチ", "hiragana": "マッチ", "meaning": "火柴"},
  {"word": "窓", "hiragana": "まど", "meaning": "窗戶"},
  {"word": "丸い/円い", "hiragana": "まるい", "meaning": "圓的"},
  {"word": "万", "hiragana": "まん", "meaning": "萬"},
  {"word": "万年筆", "hiragana": "まんねんひつ", "meaning": "鋼筆"},
  {"word": "磨く", "hiragana": "みがく", "meaning": "刷（牙）、磨"},
  {"word": "右", "hiragana": "みぎ", "meaning": "右邊"},
  {"word": "短い", "hiragana": "みじかい", "meaning": "短的"},
  {"word": "水", "hiragana": "みず", "meaning": "水"},
  {"word": "店", "hiragana": "みせ", "meaning": "店"},
  {"word": "見せる", "hiragana": "みせる", "meaning": "給...看"},
  {"word": "道", "hiragana": "みち", "meaning": "道路"},
  {"word": "三日", "hiragana": "みっか", "meaning": "三號"},
  {"word": "三つ", "hiragana": "みっつ", "meaning": "三個"},
  {"word": "緑", "hiragana": "みどり", "meaning": "綠色"},
  {"word": "皆さん", "hiragana": "みなさん", "meaning": "大家"},
  {"word": "南", "hiragana": "みなみ", "meaning": "南方"},
  {"word": "耳", "hiragana": "みみ", "meaning": "耳朵"},
  {"word": "見る 観る", "hiragana": "みる", "meaning": "看"},
  {"word": "みんな", "hiragana": "みんな", "meaning": "大家"},
  {"word": "六日", "hiragana": "むいか", "meaning": "六號"},
  {"word": "向こう", "hiragana": "むこう", "meaning": "對面、那邊"},
  {"word": "難しい", "hiragana": "むずかしい", "meaning": "困難的"},
  {"word": "六つ", "hiragana": "むっつ", "meaning": "六個"},
  {"word": "村", "hiragana": "むら", "meaning": "村莊"},
  {"word": "目", "hiragana": "め", "meaning": "眼睛"},
  {"word": "メートル", "hiragana": "メートル", "meaning": "公尺"},
  {"word": "眼鏡", "hiragana": "めがね", "meaning": "眼鏡"},
  {"word": "もう", "hiragana": "もう", "meaning": "已經"},
  {"word": "もう一度", "hiragana": "もういちど", "meaning": "再一次"},
  {"word": "木曜日", "hiragana": "もくようび", "meaning": "星期四"},
  {"word": "持つ", "hiragana": "もつ", "meaning": "拿、持有"},
  {"word": "もっと", "hiragana": "もっと", "meaning": "更加"},
  {"word": "物", "hiragana": "もの", "meaning": "東西"},
  {"word": "門", "hiragana": "もん", "meaning": "大門"},
  {"word": "問題", "hiragana": "もんだい", "meaning": "問題"},
  {"word": "八百屋", "hiragana": "やおや", "meaning": "蔬果店"},
  {"word": "野菜", "hiragana": "やさい", "meaning": "蔬菜"},
  {"word": "易しい", "hiragana": "やさしい", "meaning": "容易的"},
  {"word": "安い", "hiragana": "やすい", "meaning": "便宜的"},
  {"word": "休み", "hiragana": "やすみ", "meaning": "休息、假日"},
  {"word": "休む", "hiragana": "やすむ", "meaning": "休息"},
  {"word": "八つ", "hiragana": "やっつ", "meaning": "八個"},
  {"word": "山", "hiragana": "やま", "meaning": "山"},
  {"word": "やる", "hiragana": "やる", "meaning": "做"},
  {"word": "夕方", "hiragana": "ゆうがた", "meaning": "傍晚"},
  {"word": "夕飯", "hiragana": "ゆうはん", "meaning": "晚飯"},
  {"word": "郵便局", "hiragana": "ゆうびんきょく", "meaning": "郵局"},
  {"word": "昨夜", "hiragana": "ゆうべ", "meaning": "昨晚"},
  {"word": "有名", "hiragana": "ゆうめい", "meaning": "有名的"},
  {"word": "雪", "hiragana": "ゆき", "meaning": "雪"},
  {"word": "行く", "hiragana": "ゆく", "meaning": "去"},
  {"word": "ゆっくりと", "hiragana": "ゆっくりと", "meaning": "慢慢地"},
  {"word": "八日", "hiragana": "ようか", "meaning": "八號"},
  {"word": "洋服", "hiragana": "ようふく", "meaning": "洋裝、西式衣服"},
  {"word": "よく", "hiragana": "よく", "meaning": "常常、好好地"},
  {"word": "横", "hiragana": "よこ", "meaning": "旁邊、橫"},
  {"word": "四日", "hiragana": "よっか", "meaning": "四號"},
  {"word": "四つ", "hiragana": "よっつ", "meaning": "四個"},
  {"word": "呼ぶ", "hiragana": "よぶ", "meaning": "叫、呼喚"},
  {"word": "読む", "hiragana": "よむ", "meaning": "讀"},
  {"word": "夜", "hiragana": "よる", "meaning": "夜晚"},
  {"word": "弱い", "hiragana": "よわい", "meaning": "弱的"},
  {"word": "来月", "hiragana": "らいげつ", "meaning": "下個月"},
  {"word": "来週", "hiragana": "らいしゅう", "meaning": "下週"},
  {"word": "来年", "hiragana": "らいねん", "meaning": "明年"},
  {"word": "ラジオ", "hiragana": "ラジオ", "meaning": "收音機"},
  {"word": "ラジカセ /", "hiragana": "ラジカセ /", "meaning": "收錄音機"},
  {"word": "ラジオカセット", "hiragana": "ラジオカセット", "meaning": "收錄音機"},
  {"word": "りっぱ", "hiragana": "りっぱ", "meaning": "出色的、堂皇的"},
  {"word": "留学生", "hiragana": "りゅうがくせい", "meaning": "留學生"},
  {"word": "両親", "hiragana": "りょうしん", "meaning": "父母"},
  {"word": "料理", "hiragana": "りょうり", "meaning": "料理"},
  {"word": "旅行", "hiragana": "りょこう", "meaning": "旅行"},
  {"word": "零", "hiragana": "れい", "meaning": "零"},
  {"word": "冷蔵庫", "hiragana": "れいぞうこ", "meaning": "冰箱"},
  {"word": "レコード", "hiragana": "レコード", "meaning": "唱片"},
  {"word": "レストラン", "hiragana": "レストラン", "meaning": "餐廳"},
  {"word": "練習", "hiragana": "れんしゅうする", "meaning": "練習"},
  {"word": "廊下", "hiragana": "ろうか", "meaning": "走廊"},
  {"word": "六", "hiragana": "ろく", "meaning": "六"},
  {"word": "ワイシャツ", "hiragana": "ワイシャツ", "meaning": "白襯衫"},
  {"word": "若い", "hiragana": "わかい", "meaning": "年輕的"},
  {"word": "分かる", "hiragana": "わかる", "meaning": "明白、懂"},
  {"word": "忘れる", "hiragana": "わすれる", "meaning": "忘記"},
  {"word": "私", "hiragana": "わたくし", "meaning": "我（正式）"},
  {"word": "私", "hiragana": "わたし", "meaning": "我"},
  {"word": "渡す", "hiragana": "わたす", "meaning": "交給、遞"},
  {"word": "渡る", "hiragana": "わたる", "meaning": "過（橋）、渡"},
  {"word": "悪い", "hiragana": "わるい", "meaning": "壞的"},
  {"word": "より、ほう", "hiragana": "より、ほう", "meaning": "比…更…（比較用法）"}
]
